tosca_utils/ToscaReports.py
tosca_utils/ToscaTestcases.py
tosca_utils/TqlExecutors.py
tosca_utils/TqlGenerators.py
tosca_utils/__init__.py
tosca_utils-1.1.5.dist-info/METADATA
tosca_utils-1.1.5.dist-info/WHEEL
tosca_utils-1.1.5.dist-info/top_level.txt
tosca_utils-1.1.5.dist-info/RECORD
