Metadata-Version: 2.4
Name: tosca_utils
Version: 1.1.5
Summary: A Python Library for Tosca.
Classifier: Development Status :: 6 - Mature
Classifier: Topic :: Utilities
Dynamic: classifier
Dynamic: summary
